surveySim/__init__.py
surveySim/sim.py
surveySim/surveySim.py
surveySim/data/absolutes.ref
surveySim/data/absolutes.ref~
surveySim/data/models.ref
surveySim/data/richardson.ref
surveySim/data/rodney.ref
surveySim/data/seds.ref
surveySim/data/seds.ref~
surveySim/data/bands/bBand/tophatB.dat
surveySim/data/bands/hBand/f160w.dat
surveySim/data/bands/hBand/paritelH.dat
surveySim/data/bands/hBand/tophatH.dat
surveySim/data/bands/iBand/tophatI.dat
surveySim/data/bands/jBand/f125w.dat
surveySim/data/bands/jBand/paritelJ.dat
surveySim/data/bands/jBand/tophatJ.dat
surveySim/data/bands/jBand/tophatJ.dat~
surveySim/data/bands/kBand/paritelKs.dat
surveySim/data/bands/kBand/tophatK.dat
surveySim/data/bands/rBand/tophatR.dat
surveySim/data/bands/uBand/tophatU.dat
surveySim/data/bands/vBand/tophatV.dat
surveySim/data/examples/bells_top10.dat
surveySim/data/examples/galaxies.dat
surveySim/data/examples/limited.dat
surveySim/data/examples/liverpool.dat
surveySim/data/examples/old.dat
surveySim-0.1.2.dist-info/DESCRIPTION.rst
surveySim-0.1.2.dist-info/METADATA
surveySim-0.1.2.dist-info/RECORD
surveySim-0.1.2.dist-info/WHEEL
surveySim-0.1.2.dist-info/metadata.json
surveySim-0.1.2.dist-info/top_level.txt
