Metadata-Version: 2.0
Name: surveySim
Version: 0.1.2
Summary: UNKNOWN
Home-page: UNKNOWN
Author: Justin Pierel
Author-email: jr23@email.sc.edu
License: UNKNOWN
Platform: UNKNOWN
Requires-Dist: astropy
Requires-Dist: numpy
Requires-Dist: scipy
Requires-Dist: sncosmo
